{
  "type_description_msg": {
    "type_description": {
      "type_name": "slam_toolbox/srv/ClearQueue",
      "fields": [
        {
          "name": "request_message",
          "type": {
            "type_id": 1,
            "capacity": 0,
            "string_capacity": 0,
            "nested_type_name": "slam_toolbox/srv/ClearQueue_Request"
          },
          "default_value": ""
        },
        {
          "name": "response_message",
          "type": {
            "type_id": 1,
            "capacity": 0,
            "string_capacity": 0,
            "nested_type_name": "slam_toolbox/srv/ClearQueue_Response"
          },
          "default_value": ""
        },
        {
          "name": "event_message",
          "type": {
            "type_id": 1,
            "capacity": 0,
            "string_capacity": 0,
            "nested_type_name": "slam_toolbox/srv/ClearQueue_Event"
          },
          "default_value": ""
        }
      ]
    },
    "referenced_type_descriptions": [
      {
        "type_name": "builtin_interfaces/msg/Time",
        "fields": [
          {
            "name": "sec",
            "type": {
              "type_id": 6,
              "capacity": 0,
              "string_capacity": 0,
              "nested_type_name": ""
            },
            "default_value": ""
          },
          {
            "name": "nanosec",
            "type": {
              "type_id": 7,
              "capacity": 0,
              "string_capacity": 0,
              "nested_type_name": ""
            },
            "default_value": ""
          }
        ]
      },
      {
        "type_name": "service_msgs/msg/ServiceEventInfo",
        "fields": [
          {
            "name": "event_type",
            "type": {
              "type_id": 3,
              "capacity": 0,
              "string_capacity": 0,
              "nested_type_name": ""
            },
            "default_value": ""
          },
          {
            "name": "stamp",
            "type": {
              "type_id": 1,
              "capacity": 0,
              "string_capacity": 0,
              "nested_type_name": "builtin_interfaces/msg/Time"
            },
            "default_value": ""
          },
          {
            "name": "client_gid",
            "type": {
              "type_id": 51,
              "capacity": 16,
              "string_capacity": 0,
              "nested_type_name": ""
            },
            "default_value": ""
          },
          {
            "name": "sequence_number",
            "type": {
              "type_id": 8,
              "capacity": 0,
              "string_capacity": 0,
              "nested_type_name": ""
            },
            "default_value": ""
          }
        ]
      },
      {
        "type_name": "slam_toolbox/srv/ClearQueue_Event",
        "fields": [
          {
            "name": "info",
            "type": {
              "type_id": 1,
              "capacity": 0,
              "string_capacity": 0,
              "nested_type_name": "service_msgs/msg/ServiceEventInfo"
            },
            "default_value": ""
          },
          {
            "name": "request",
            "type": {
              "type_id": 97,
              "capacity": 1,
              "string_capacity": 0,
              "nested_type_name": "slam_toolbox/srv/ClearQueue_Request"
            },
            "default_value": ""
          },
          {
            "name": "response",
            "type": {
              "type_id": 97,
              "capacity": 1,
              "string_capacity": 0,
              "nested_type_name": "slam_toolbox/srv/ClearQueue_Response"
            },
            "default_value": ""
          }
        ]
      },
      {
        "type_name": "slam_toolbox/srv/ClearQueue_Request",
        "fields": [
          {
            "name": "structure_needs_at_least_one_member",
            "type": {
              "type_id": 3,
              "capacity": 0,
              "string_capacity": 0,
              "nested_type_name": ""
            },
            "default_value": ""
          }
        ]
      },
      {
        "type_name": "slam_toolbox/srv/ClearQueue_Response",
        "fields": [
          {
            "name": "status",
            "type": {
              "type_id": 15,
              "capacity": 0,
              "string_capacity": 0,
              "nested_type_name": ""
            },
            "default_value": ""
          }
        ]
      }
    ]
  },
  "type_hashes": [
    {
      "type_name": "slam_toolbox/srv/ClearQueue",
      "hash_string": "RIHS01_5ae7286887351a43cd6265cbd3ec3fdf0074fa6e9f39c17057351b6ab4415477"
    },
    {
      "type_name": "builtin_interfaces/msg/Time",
      "hash_string": "RIHS01_b106235e25a4c5ed35098aa0a61a3ee9c9b18d197f398b0e4206cea9acf9c197"
    },
    {
      "type_name": "service_msgs/msg/ServiceEventInfo",
      "hash_string": "RIHS01_41bcbbe07a75c9b52bc96bfd5c24d7f0fc0a08c0cb7921b3373c5732345a6f45"
    },
    {
      "type_name": "slam_toolbox/srv/ClearQueue_Event",
      "hash_string": "RIHS01_8c487d1ec21401b600495e318d20fc6ca6d9d73290918eaa8b4085c873b2b4e9"
    },
    {
      "type_name": "slam_toolbox/srv/ClearQueue_Request",
      "hash_string": "RIHS01_5be39ec92b1c3d67d72d9d332a5e5e84c12fbfe36efaf9311c7ecbe32340edb5"
    },
    {
      "type_name": "slam_toolbox/srv/ClearQueue_Response",
      "hash_string": "RIHS01_091b71de50c6325803533b815ec0a4d39a571c0d5641e5ea5cefffe4d70c1490"
    }
  ]
}